{
  "$id": "1",
  "strings": [
    {
      "Key": "6c765912-14b6-4970-9aaf-40bcdb57ee2f",
      "Value": "{g|Arcane4_1}[选择效果]{/g} “我不准这个死灵法师在我的领地中练习他的黑魔法。”"
    },
    {
      "Key": "c06355e7-85d0-44a7-ad85-dbdaa70faab0",
      "Value": "{g|Arcane4_2}[选择效果]{/g} “他的提议听起来很靠谱，死灵法师将取得他的许可。”"
    },
    {
      "Key": "a6084274-67cf-4fce-b188-59cc18ffc8b3",
      "Value": "“在这件事上我会采信你的建议。”"
    },
    {
      "Key": "70b71eed-6f4c-43c4-a9d3-b8e4d93bd394",
      "Value": "“我有个消息，每天都有越来越多的法师来到我们的都城——似乎正围绕着魔法物品鉴定师形成一个小型的法师社群：新的书店、新的炼金工房、甚至现在还有幻术师开的店！那位女士能凭借幻术做出多到无法想象的衣裙、妆容和发型！特别适合出席晚宴——只是要记得在法术消失前回家！”"
    },
    {
      "Key": "83c68394-a43c-4a38-abe6-2f26322356e5",
      "Value": "“我很高兴地告知{mf|阁下|阁下|殿下|殿下}，魔法的技艺已经在我们的领地上如花绽放，每一天都有越来越多的魔法使用者蜂拥而至，进入我们的都城。一个多样化的法师社群已经围绕着魔法物品鉴定师开始形成——书店、炼金工房甚至是幻术师的店。然而，这样的快速增长也吸引了更多……可疑的从业者。”"
    },
    {
      "Key": "eaf6f88b-6307-43c5-aae5-8f2c0b5a3801",
      "Value": "“这种神秘的技艺正逐渐在你的都城扎根……在这样一个落后的时代正如预期。如同蚁群聚集于土丘，越来越多的人聚拢在魔法物品鉴定师的周围。他们自豪地向他展示那些鬼画符一般的卷轴和蒲公英酊剂！但其中一个人尤其搞笑……”"
    },
    {
      "Key": "b0c5f5a3-c5ea-4f84-8f7b-5fac59218b75",
      "Value": "“然而……这次扩张也引来了黑暗的一面。一名盖布来的死灵法师正寻求在你的领地里开店。——他想要召唤不死仆从，并把它们作为廉价劳力出租！在他的故乡，骷髅耕田、砍树、挖矿……但在世界上其他地方死灵法术都是被严格禁止的，因为要操纵一具死尸，必须要取得一小片曾经寄身其中的灵魂！我们的这位来访者向你申请许可。作为回报，他答应给我们提供一批新的‘工人’……”"
    },
    {
      "Key": "82d18acf-6607-42d5-9b6e-b4507477d759",
      "Value": "“一位从盖布来的大死灵法师找过我。鉴于他的技艺在世界各地都被视为非法并遭到诋毁，他向我们提出了一项协议。我们为他提供许可，允许他供应‘无生命劳动力租赁服务’——这意味着我们将允许他召唤不死劳工，并把它们出租给农场、锯木厂和仓库。作为谢礼，他将为我们提供他的第一批‘工人’。”"
    },
    {
      "Key": "5f5971ea-7c84-47d8-8964-5a37f8a0fe80",
      "Value": "“一个只关心鸡零狗碎的小贩，竟敢自称死灵法师，还要我听他的诉求。他恳求我们授予他许可，允许他唤起不死的奴仆，然后租给农场、锯木厂和矿场去做工。超越死亡本身的力量、亡者的灵魂、甚至是生命永恒的秘密——全都在他的面前！但他唯一的念头竟然是出租农场劳动力！”"
    },
    {
      "Key": "e0fe3f4f-7b83-4e66-ad09-f312aa82a8f1",
      "Value": "“好极了！我希望当我把消息告诉这个靠尸体为生的家伙时，他就会马上永远离开都城。”"
    },
    {
      "Key": "5e1cab9a-ce8d-4ddf-9ac7-b6885c729d75",
      "Value": "“我全力支持这个决定，{mf|阁下|阁下|殿下|殿下}。”"
    },
    {
      "Key": "ee7c0326-e6a9-4103-8146-ed078224a569",
      "Value": "{n}“梅戈”带着残酷的满足感向你鞠躬致敬。{/n}“我会把您的决定告诉死灵法师。我们这片土地的权能与力量将不断增长，变得多元化。”"
    },
    {
      "Key": "103b9d5f-13d0-4c08-bdde-be791c405893",
      "Value": "“我会告知死灵法师，他的黑暗技艺在这片土地没有容身之所。”"
    },
    {
      "Key": "0ead3a34-b1d5-4f75-ae14-00d9a1b6839c",
      "Value": "“他向我保证他只使用‘自愿捐赠的材料’——即在死前签订了合同的农民的尸体。尽管如此，我仍然建议你拒绝他的提议。别忘了死灵法师必须切下一小片死者的灵魂，才能让尸体动起来。还请您记住，我们活生生的工人根本无法与不死奴隶竞争。这样一来我们的民众只会变得更穷——还得被迫以更低的价格出卖自己的劳动力。这将导致一个恶性循环，使我们的国家逐渐完全依赖于死灵法师的服务。”"
    },
    {
      "Key": "a1b515ee-0983-4b30-8cd1-cd552f5d8a27",
      "Value": "“光是想想就让我觉得恶心。他发誓只使用那些在生前签订合同，出售自己遗体来换取几枚金币的人。然而，我毫不怀疑这会导致各种各样的麻烦。首先，胆大的市民会购买铁锹，并养成每晚拜访墓地的习惯。然后乞丐和孤儿将开始从街头消失……不，{name}，我们不能让这种事情发生！”"
    },
    {
      "Key": "5e917e4c-057e-4fdd-8ea1-54b842cde177",
      "Value": "“尽管如此，如果我们授予他许可，他就承诺向我们提供他的第一批‘工人’作为回报。我们当然应该同意他的申请。无论他的造物多么可怜，一个不死奴隶总是比一个活人更有价值。不死生物永远不会疲劳，也不会生病，他们无条件服从命令，他们不需要报酬，不需要食物，也不需要休息——甚至连光都不用。”"
    }
  ]
}