{
  "$id": "1",
  "strings": [
    {
      "Key": "5b1acccd-3f77-4b05-b1be-ae223c36365b",
      "Value": "“阁下！赞美众神！您是我们的救星，您救了我们！”"
    },
    {
      "Key": "c0d0e12c-3b83-4402-a34d-762df91461d0",
      "Value": "“不仅是我，还有我的人民！我愿意做任何事来表达我的谢意，我……？”{n}{d|Varn}梅戈{/d}停顿了一下，似乎陷入了沉思，随后开始嘟嘟囔囔，{/n}“赛弗尔没能活着看到这个场面，真是太遗憾了。还有冈德森……他不是坏人，只是……太过冲动。”{n}梅戈点了点头，{/n}“我们会为他们哀悼，为所有因沃达凯而失去生命的人哀悼。然后……”"
    },
    {
      "Key": "747256ba-3049-430a-9bc2-34ea12db9e59",
      "Value": "“发生在我的人民身上的事……是一场可怕的损失……男人、女人甚至儿童，沃达凯没有放过任何人！扼杀无辜者的生命，何其野蛮，它……”{n}梅戈捏紧了拳头，最终还是让自己镇静了下来。{/n}“他们将被哀悼，我们将纪念死去的人。然后……”"
    },
    {
      "Key": "e44d96ea-c689-470e-9c01-0921f36bba9f",
      "Value": "{n}梅戈转过来，庄重地面向你：{/n}“阁下……相救之恩难以为报，瓦恩领与我现在效忠于您。那些来自北方的懦夫在我们最需要的时候连根手指都没有抬一下，因此我将把我的剑交给仗义相助之人。”{n}他低下了头，{/n}“我将前往您的城堡，并在那里等您。我的代理人将负责治理{g|Varnhold}瓦恩领{/g}，我会指派一个值得信任的人，您不必为此担心。”"
    },
    {
      "Key": "ce5d7627-b10d-46bd-afa8-a8926160bb2e",
      "Value": "“至于{g|Varnhold}瓦恩领{/g}的人民……我想这个镇子不会空很久的。待在那些罐子里……”{n}他咳嗽了一下。{/n}“这么说吧，会让人十分怀念以前的美好生活……包括和某个温暖的身体一同分享床榻。”{n}他眨眨眼。{/n}“我想不久之后瓦恩领的人口就要翻倍了。”"
    }
  ]
}