{
  "$id": "1",
  "strings": [
    {
      "Key": "c37f1a20-ef86-4bb0-bfdf-9e077fcad06b",
      "Value": "{g|Culture5_2}[选择效果]{/g} “我们应该批准这位年轻作曲家的请求。”"
    },
    {
      "Key": "9919cda2-1044-41d9-9920-beb6213589cc",
      "Value": "“我们不能干涉创作的过程。即使作曲家求我们也不行。拉齐奥不可以住在我的城堡里。”"
    },
    {
      "Key": "410b69eb-9388-439a-831f-e27389156550",
      "Value": "“你自己决定吧。”"
    },
    {
      "Key": "3b4a2077-3377-4691-85ce-9bd6cac3f694",
      "Value": "{g|Culture5_1}[选择效果]{/g} “我对你的计划没有任何意见，耶萨尔。去协助作曲家，看看他的进展如何！”"
    },
    {
      "Key": "bcecfd9d-bd09-48f9-bebf-8d053608e066",
      "Value": "“简直太不可思议了，{name}！要是你也能看见就好了！他眼中的炽热！他的灵魂太纯粹了！他的心灵是如此高尚！我们应该——不，我们必须帮助他！"
    },
    {
      "Key": "cc995d2d-3c39-4ec1-a8dd-30089ec133d7",
      "Value": "“您好，{mf|阁下|阁下|殿下|殿下}。昨天发生了一件稀奇的事。我在傍晚散步的时候，遇到了一个年轻人。他名叫拉齐奥·梅苏斯，是一位来自{g|Absalom}安布萨朗{/g}的年轻作曲家。他告诉我他离开故乡四处寻找灵感。他对您登上王位的故事感到惊讶，{mf|阁下|阁下|殿下|殿下}。——事实上，这故事给他留下了深刻的印象，他决心为此写一部的歌剧。”"
    },
    {
      "Key": "a8ef51ca-d688-43a7-a062-775d38854dc3",
      "Value": "“最近，一位热情洋溢的年轻作曲家抵达了都城。他正在寻求我的关注。我告诉他，他已经是闻名{g|Absalom}安布萨朗{/g}的希望之星了。他的第一章部作品受到评论家们的热烈欢迎——尤其是贵妇。据说他颇为英俊。”"
    },
    {
      "Key": "a26a264e-4e1b-4dd8-aa7c-b6de8af04bf3",
      "Value": "“昨天晚上，我遇到了一位极其出色的年轻作曲家，来自{g|Absalom}安布萨朗{/g}！他名叫拉齐奥·梅苏斯，还没有获得与他的才能相称的荣耀。我以{g|Shelyn}雪琳{/g}的恩宠发誓，他一定会出名的！他离开故乡四处取材，当他踏上我们的土地时，对您成功的故事惊讶不已。“"
    },
    {
      "Key": "2dc630c5-9f23-4d14-9b68-a09e04c58c76",
      "Value": "“他请求获准在王宫内生活与工作，这样就能从现实生活中取材来描绘您的角色。尽管如此，我认为我们应该拒绝他。艺术必须是自由的！”"
    },
    {
      "Key": "591f09b3-e8ab-43f2-ae5a-0ae096c92eb0",
      "Value": "“他名叫拉齐奥·梅苏斯，他需要您的庇护。他一直在寻找新鲜的素材，然后听说了您登上王位的故事。这故事给他留下了深刻的印象，他梦想为此写一部的歌剧。他很年轻，天真又缺乏经验，但这也使得他更为有用。我们应该把他安置在王宫里，并给他资助。我会回答他所有的问题。按适当的顺序整合他的想法并不困难。”"
    },
    {
      "Key": "f080dcbf-5672-4172-b3f6-e04e955739dc",
      "Value": "{n}琳翠微笑着鼓掌。{/n}“我保证，{name}，您不会为您的慷慨感到遗憾的！”"
    },
    {
      "Key": "0fe68296-552f-4661-8748-bc902a752357",
      "Value": "{n}精灵点头，面露微笑。{/n}“好极了。”"
    },
    {
      "Key": "90d95c48-c2f2-42f4-9d59-697a2bfe8d1f",
      "Value": "“感谢您的信任，{mf|阁下|阁下|殿下|殿下}。到时候，我们将看到自由对艺术家和他的创作产生的积极影响。”"
    },
    {
      "Key": "b0c7d303-93a4-4ae5-bc87-f756ec75f293",
      "Value": "“没有别的办法了！拉齐奥会和我们住在一起！噢天啊，这一定会让他非常开心！”"
    },
    {
      "Key": "289f1ab7-6c76-4e8f-a70d-b1fa2778c475",
      "Value": "“他说他一直梦想以您的冒险写一部歌剧！他只想住进您的王宫创作音乐，这样一来他就能尽可能接近您和您队伍里的每个人了！我敢肯定，是命运把他带到了我们门前——如果我们没有支持这位年轻的天才，命运一定不会放过我们的！”"
    },
    {
      "Key": "85160274-9a62-4bc8-9abd-693b42c6da77",
      "Value": "“住在这里会让他觉得对我们负有义务。每天都见到您，他就会失去冷静的观察距离。每位艺术家都需要靠这距离来清楚地审视他的表现对象！他会难以理解你现在的决定，但这种自由对他大有好处。一朵生长在温室里的花，在遭遇第一丝寒意的时候就会枯萎凋零！而路边的野草，无论面临什么样的考验，都会在干旱和暴风雨中坚定不移。”"
    },
    {
      "Key": "c407182f-32f5-4046-8fb2-a74586e2b223",
      "Value": "“他的歌剧不仅会使您的大名流传千古，在当下还能向农民传递信息。他们会明白应该多么感激您的不懈努力，如此一来，除了为他们强大而开明的统治者竭诚效力，他们再不会有别的想法。至于我，我不介意和这位年轻人一起共处一段时间。您知道我喜欢欣赏各种各样的花哨小玩意：鲜花、宝石、天真无邪却令人赞叹的年轻人……”"
    }
  ]
}