{
  "$id": "1",
  "strings": [
    {
      "Key": "f185ea7f-973d-4e66-866f-b468d862b248",
      "Value": "“你没有时间来调查我的谋杀案，真是可惜。我最主要的证据，也就是老法桐那里的那只野猪尸体，已经被那里的野生动物或是饥饿的农民撕成碎片。另外，商人恩尼奥也成功逃走。所有的线索都已经断了。现在我们也只能把这件事抛诸脑后了。”"
    },
    {
      "Key": "74117b64-3022-42b9-9418-49fb950d4669",
      "Value": "“真是可惜，你没有时间来继续调查我的谋杀案。我听说有一群旅行者来到了{g|Thorn River}荆棘河{/g}的岸边，就在野猪出现在老法桐树前的地方。但现在旅行者们已经走了。另外，商人恩尼奥也成功逃走。线索全断了。”"
    },
    {
      "Key": "d5c7301f-cff4-4975-b6ff-cae4d8291707",
      "Value": "“真可惜，你都没空去看看恩尼奥。他设法逃走了，而他的随身物品则被几个小偷偷走了。现在线索都断了。”"
    }
  ]
}