{
  "$id": "1",
  "strings": [
    {
      "Key": "6f8d71db-096a-4f1a-9965-7f0ab1433664",
      "Value": "“法术没了。我要休息。”"
    },
    {
      "Key": "6e977d23-c009-4233-bed5-910818d46027",
      "Value": "“又把魔法用完了。基本没剩下。”"
    },
    {
      "Key": "8804d2cc-38e5-422f-9060-735c172b88bb",
      "Value": "“也许我们可以派诺克诺克去科技联盟卧底？反正他怎样也会逃跑的，但在那之前，他肯定能给那群畜生搞出一大堆麻烦，叫他们再也没工夫做施法奴隶生意了！”"
    },
    {
      "Key": "b26ed893-15c7-4fbc-b831-aa04d14f5277",
      "Value": "“呵，诺克诺克，魔法。嘿嘿嘿嘿……哦，别那么看我！听起来就好笑，啊哈哈！”"
    },
    {
      "Key": "cb52f04d-4546-46a6-aeff-5adbc1034c19",
      "Value": "“地精法师……我的不可思议之物大全又多了一项奇谈！”"
    },
    {
      "Key": "fce8fb03-4049-4e8b-b548-9e52c2a72aaa",
      "Value": "“动用超越自身理解的力量只会加快你的灭亡。然而，我并不会为此悲伤，因为这是你自己选择的道路。”"
    },
    {
      "Key": "cbc0a95c-860a-4210-9731-32e56f435a27",
      "Value": "“会魔法的地精就像一只长着龙头的小猫咪：有趣——但依然很危险！”"
    },
    {
      "Key": "a31ddcb2-756b-4d07-9908-5e3cc561bae9",
      "Value": "“会魔法的地精就像一只长着龙头的小猫咪：有趣——但依然很危险！”"
    }
  ]
}