{
  "$id": "1",
  "strings": [
    {
      "Key": "fdb1b613-15b7-4e21-b9ee-e6d75c0b36b1",
      "Value": "我们说出了无面姐妹告诉我们的那个词。"
    },
    {
      "Key": "3b24957d-c1c5-4b88-bdb4-348bafe36c5a",
      "Value": "我们在这个地方做了个标记，然后就离开了。"
    },
    {
      "Key": "ecffca4a-6367-484d-a458-e9c85300b015",
      "Value": "……检查了这名无面姐妹的尸体。"
    },
    {
      "Key": "8c539238-9af1-4add-91cd-46b70d3c1010",
      "Value": "……取得了香炉，并离开了古墓。"
    },
    {
      "Key": "5829e6cf-4b68-41b8-b667-ee07ba1f4e76",
      "Value": "[继续]"
    },
    {
      "Key": "ad0e486a-8ebf-49f2-8afe-5ece8fba9ade",
      "Value": "……继续沿着走廊前进。"
    },
    {
      "Key": "1ec4887d-583f-4d9b-9ea2-bd0e04ce6a31",
      "Value": "……仔细地检查了墙上的霉菌。"
    },
    {
      "Key": "ff817a89-d561-4e60-9f71-cfb678ea6e8f",
      "Value": "……检查走廊里是否有魔法。"
    },
    {
      "Key": "037d0456-7d3f-4d4b-b24c-dfcbda09dc3c",
      "Value": "……试着清掉了墙上的霉菌。"
    },
    {
      "Key": "1fe4eee7-b2e7-4d7b-9b0c-c751c907a0aa",
      "Value": "……仔细地检查走廊里是否有陷阱。"
    },
    {
      "Key": "257cec7b-ce51-4fcb-91b7-da7e581e2510",
      "Value": "……阅读了这些铭文。"
    },
    {
      "Key": "ba0cd861-98e7-47d2-8048-db56025810ba",
      "Value": "[关闭]"
    },
    {
      "Key": "4400f7ac-6ba2-42ad-be43-d474dd874c1b",
      "Value": "……查看墓穴和香炉，试图弄明白为什么无面姐妹需要这些诡异的东西。"
    },
    {
      "Key": "ea53874f-399c-40b7-9db1-2052838f772a",
      "Value": "古代的独眼巨人在这些中空的岩石里修建了这座古墓，通向古墓的道路也通过茂盛的植被巧妙地遮掩了起来，不仔细寻找很难发现。要不是事先知道，我们很可能也会忽略掉这个地方，根本想不到入口在这里。一块巨大的石板封住入口，和四周的石墙几乎融为一体，不过上面杂乱的草木和被扯断的藤蔓表明这块石板最近被人移动过……"
    },
    {
      "Key": "01cec5aa-f48b-442d-a140-a807e42427c3",
      "Value": "门后是一条宽敞的走廊，很明显是为体型比人类大得多的生物修建的。这里的空气非常潮湿，雕刻着浮雕和花纹的石墙上覆满了一种油腻恶心的霉菌。我们……"
    },
    {
      "Key": "e9bd3daf-646f-4d48-b034-daf9bfeeea3f",
      "Value": "上面说：\n“动物有两只眼。\n人有一只。\n神灵没有，因其居住在黑暗中。\n黑暗拥有一切答案，打开所有门户，连通所有道路。”\n这些古代的独眼巨人真是一群欢乐的家伙啊！"
    },
    {
      "Key": "16e533af-431e-4599-ba29-edad5eb2b289",
      "Value": "“Kheb”的意思是“黑暗”。这是一种古老的、被遗忘的语言里的一个同样古老的、被遗忘的词语，就像是荒野中一只不知名的野兽身上的一块被时间漂白了的骸骨。在说出这个词语以后，石板平顺地向一侧移开，几乎悄无声息，后面的入口通向了一片潮湿、发霉的黑暗中。为了避免被困在里面，我们用一块巨大的石头顶住了石门；当我们一踏进去，石门就开始震动起来，想要关上，但却被那块石头顶住无法移动。幸好我们留了一手啊。"
    },
    {
      "Key": "0cad2c99-4d96-4cd7-872a-6ffeaa036dca",
      "Value": "虽然长满了霉菌，但是石墙上的雕刻保存地非常完好。"
    },
    {
      "Key": "a9af2fd5-293d-4b84-8f1b-09de3d73989f",
      "Value": "虽然这座古墓里的霉菌非常粘稠、恶心、酸臭无比，但幸运的是它对人类无害。了解到了这一点之后，我们……"
    },
    {
      "Key": "46daa7f6-d5b7-4a3f-bf8f-796c05a11086",
      "Value": "有的时候，地下城里的真菌可能会比任何怪物都要更危险。已经有无数的冒险者被有毒的孢子感染、窒息而死，或是被烧死，又或是当场溶解。仅仅是因为他们从来没想过要学习一些植物学知识。"
    },
    {
      "Key": "4d707938-7b53-4913-91fc-33382bf4eb69",
      "Value": "唉，我们无法判断这份样本是否危险。我们现在唯一的选择就是拼拼运气了。我们……"
    },
    {
      "Key": "3644c7fa-8c92-43f9-ac2e-cf11a5ad386f",
      "Value": "墙上有种什么东西被覆盖在一层霉菌之下，但在魔法灵视之下却发出了明亮的光芒，散发出一片强烈的死灵法术灵光。这肯定是某种魔法陷阱，你最好还是不要去直视这种符号。考虑到这点以后，我们……"
    },
    {
      "Key": "36283035-b67d-4b6b-8bf0-7adc73c02726",
      "Value": "这座古墓也不例外。没错，地板上并没有任何的压板，也没有一大堆石头会突然砸到我们头上，但是在一层霉菌之下藏着一个魔法符号，你最好还是不要去看。"
    },
    {
      "Key": "cae07279-80dd-4385-a2bc-7db8169094ae",
      "Value": "但似乎这座古墓还真是个另类。我们没有找到任何的机关陷阱，至少地板上没有任何的压板，也没有一大堆石头会突然砸到我们头上。"
    },
    {
      "Key": "cc4b5e82-1629-4019-85c7-f397eb4c214b",
      "Value": "古墓和陷阱永远是形影不离的，就好比是笔和墨，野蛮人和愤怒，或者官老爷和贿赂！"
    },
    {
      "Key": "ef890787-514f-4bed-ac6a-7a61c348341d",
      "Value": "我们对此百思不得其解。"
    },
    {
      "Key": "125b0d39-d699-4177-af1c-32c27974875c",
      "Value": "我们小心翼翼地从墙上刮下了一些霉菌。没关系，这是一种完全无害的霉菌，和你之前遇到过的那些有毒的、强酸性的、或者鬼才知道是什么东西的霉菌品种完全不一样。在被霉菌掩盖之下的墙上，我们找到了一些文字，这些独特的、清晰可见的字母属于某种未知的语言。"
    },
    {
      "Key": "7084ef30-c504-40af-a9a2-cee5535a9c47",
      "Value": "当然，我们远远地避开了那个藏着魔法符号的地方。完成了以后，我们……"
    },
    {
      "Key": "51dd0a4c-ba94-483f-90b1-33d09e0ad62a",
      "Value": "看来这些霉菌很安全，但是覆盖着霉菌的墙上却藏着一个令人不那么愉快的惊喜。在清理掉一片霉菌之后，我们发现了一枚硕大的、非常清晰的魔法符号。虽然我们立刻就明白这个符号有什么作用，但是已经太迟了。这枚符号亮起了诡异的光芒，我们膝盖一弯，原来是符号上散发出的魔法能量将虚弱诅咒施加在了我们身上。在过了一段时间之后，我们终于又重新恢复了镇定，虽然有些勉强，然而……"
    },
    {
      "Key": "5d45459c-905e-4853-b0b0-7d0b3e81341e",
      "Value": "完成搜索以后，我们……"
    },
    {
      "Key": "718405ea-de48-4937-ae2f-04d82542448d",
      "Value": "一副巨大的石棺摆放在墓室的正中央，棺盖放在一旁的地上。石棺里面躺着一副巨大的骸骨，颅骨上只有一个硕大的眼窝，空洞地望着正上方。它的指骨紧紧地握着一个小型的黄铜香炉，香炉本身也很像一枚只有一个眼窝的头颅。在石棺附近还倒着一个穿着灰色斗篷的瘦削女性。她已经没有呼吸了，而且不难看出她的死因。这些独眼巨人们为胆敢前来盗墓的人留下了一个致命的惊喜，在骸骨的头部附近有一枚死亡魔法符号刻在石棺的表面。看来这名无面姐妹一打开棺盖就立刻被这个魔法符号给杀死了。幸好这个陷阱只能用一次。我们……"
    },
    {
      "Key": "cd769a6a-04bb-45cf-9d86-36fb06d4ee66",
      "Value": "当我们取下这名死去的女人脸上的面纱以后，一股寒意沿着我们的脊背直冲后脑，她真的没有脸。取而代之的是一片粗糙的灰色表皮，就像是胡乱捏制的一张陶土面具。上面用两个洞代替了眼睛，又用另一个洞代替了鼻子，还有一道裂缝就是嘴……到底是什么力量把她变成了这样？"
    },
    {
      "Key": "43131f81-52fb-4084-ad22-170619a009d1",
      "Value": "检查过这具尸体以后，我们发现这个死去的女人并不是人类。她是一个妖精，很有可能是一只水妖精，但是她的身体被某种未知的魔法给扭曲了。"
    },
    {
      "Key": "fa9543cb-9648-475a-85d3-48d4c71d8ded",
      "Value": "她的尸体没有任何值得关注之处，所以我们取走了香炉，离开了这座古墓。这座古墓也就成为了我们要寻找的人的葬身之地。"
    },
    {
      "Key": "12b5184d-5011-4fcc-8a07-3584822df454",
      "Value": "从墙上的雕刻来看，建造了这个阴森地方的人必然敬仰{g|Charon}卡戎{/g}——力量接近神灵的死神大邪魔。在他仆从的仪式中也用到了类似的香炉。从眼窝中冒出的烟象征着一个灵魂飞向了他……无面姐妹是在举行什么仪式吗？或许是在尝试召唤卡戎？太可怕了！"
    },
    {
      "Key": "9ca04134-30e0-49cd-b5ca-2e436b01fd19",
      "Value": "无论在这阴森的地方探索多久，我们就只弄明白了一件事——这里的建造者热衷头骨。"
    },
    {
      "Key": "7bbcb6f5-1427-41b5-a080-c8f742fcbba9",
      "Value": "探索坟墓后，我们……"
    }
  ]
}