{
  "$id": "1",
  "strings": [
    {
      "Key": "bddf0a1f-3688-46ad-ab6d-6c18b6804c7a",
      "Value": "“兰德尔，这是怎么了？终于决定要参战了吗？但是你现在来恐怕是有点晚了啊！”"
    },
    {
      "Key": "aa0894b8-ca98-4b6f-8042-67c8d3cbac7e",
      "Value": "“哈，俏皮话倒是说的不错！你是不是天天在镜子前面反复练习这番话啊？”"
    },
    {
      "Key": "0efde3e7-1627-40bd-b309-a217cdbbabae",
      "Value": "“你这个人渣！想要从背后偷袭我，是吗？！”"
    },
    {
      "Key": "4238ad14-b736-402c-a372-c7e3eae82232",
      "Value": "“你到底想要什么？”"
    },
    {
      "Key": "c6a81b9c-f247-4925-b4e3-fd0dbe7c8e63",
      "Value": "“就算你成功地杀死我，你真的觉得你可以夺去我的土地吗？”"
    },
    {
      "Key": "702f8aaa-ec69-4dfb-baca-9281aa992dea",
      "Value": "“所以你觉得你可以赢过我吗，你这个小杂种？”"
    },
    {
      "Key": "16555d2e-c838-48ef-915a-4d3717814977",
      "Value": "“所以我们贵族之间就一定要勾心斗角咯？我已经开始后悔接受{mf|男爵|女爵}这个头衔了。”"
    },
    {
      "Key": "17870ef5-6f23-4fa2-860d-62b4f32e5c02",
      "Value": "“如果你真的聪明，为什么要亲自屈尊来杀我呢？为什么还要告诉我你的计划呢？”"
    },
    {
      "Key": "207c8b54-a9d1-4c22-b78d-a256e13693ce",
      "Value": "“不要再说废话了。你想要干掉我？那就来试试吧！”"
    },
    {
      "Key": "9fa57d76-845e-4a45-a9b8-b3a7704b94fe",
      "Value": "“兰德尔啊，兰德尔……我还以为我们是朋友呢！”"
    },
    {
      "Key": "2dd9935f-1aa8-4996-9bd8-9268145847ae",
      "Value": "{n}兰德尔·{g|House Lebeda}勒贝达{/g}从一群打手身后向你露出微笑。他举起一只手，用嘲讽的态度向你问候。{/n}“你好啊，勇敢的{g|Stolen Lands}失窃之地{/g}征服者！请允许我向你表示祝贺，今天，你的名字将会名垂青史！”"
    },
    {
      "Key": "2d29e99b-58f6-455a-aa11-c06f0f40e9ac",
      "Value": "“我想说，我来得正是时候，有足够的的时间可以告知阿尔多瑞夫人你是如何在和野蛮人的战斗中英勇牺牲的！”"
    },
    {
      "Key": "34aeeb43-6b0d-4f36-8633-08950f8e9bd8",
      "Value": "“哦，你什么都不懂。当我们两个人第一次跨过边界，进入这片将来一定会属于我的土地时，我就已经练习过了！”"
    },
    {
      "Key": "4eba91bc-3cf6-4d13-a476-327c152ba74b",
      "Value": "“真粗鲁！你真的希望你的遗言是一句脏话吗？嗯，看来等我以后写回忆录的时候，我得雇一个写手，帮你重新攥写一篇更加恰当的遗言！”"
    },
    {
      "Key": "a71c73fd-ae84-4555-8dd8-96ff076e35be",
      "Value": "“还不明显吗？当然是你的领地了。我即将获得{g|House Lebeda}勒贝达家族{/g}的继承权。现在我们正计划扩张我们的领地，获取更多的荣誉！十年以后，大家都会知道是英勇的兰德尔·勒贝达征服了整个{g|Stolen Lands}失窃之地{/g}。只有研究历史的专家才会对{Name}这个名字有所耳闻，兰德尔麾下的这名将军在与野蛮人的战斗中牺牲了。不过别担心，我会让他们用最华丽的辞藻来歌颂你的故事。说不定我还会雇一名吟游诗人来为你的壮烈牺牲写一首歌呢！”"
    },
    {
      "Key": "fb3dff66-122d-495a-9f12-6210a9b6e6f4",
      "Value": "“还能是谁的？据我所知，{kingdomname}的{mf|男爵|女爵}并没有留下子嗣。当旗帜从你的手中滑落时，我会接过来。而如果我的子民想要反对……嗯，其实这段时间我并没有虚度。我在想你的手下里有多少人还对你保持忠诚。你猜，已经有多少人投入到了我的麾下？”"
    },
    {
      "Key": "4a38c4e6-d09a-40f1-ab97-58974bfb7644",
      "Value": "“你真的不应该低估我。你觉得年龄代表着劣势吗？只有出身贫寒的普通人，像你这样的人，才会用一个人的年纪来评判他的实力。一名贵族的实力还应该包括他的家族在数个世纪中存续的时间！”"
    },
    {
      "Key": "13440604-defc-4193-91aa-d817fef2232c",
      "Value": "“‘我们贵族’？”{n}兰德尔大笑起来。{/n}“你真的把自己当做贵族了吗？你真的相信你所谓的头衔很值钱吗？也许你的曾曾曾孙子可以有资格到我的家族宅邸厨房来做工，当然前提是你得活下去，给你家留下了子嗣！”"
    },
    {
      "Key": "2b655598-35b2-4a5c-a2ad-e0f9319d802f",
      "Value": "“你知道我家族的信条吗？‘做事要优雅，不然就是傻。’背后捅刀子，酒杯里下毒，暗巷仙人跳……这是{g|House Surtova}瑟托瓦{/g}家解决问题的方式。不，这是我第一次获得如此重大的胜利。我想要亲自看一看，看着你的眼睛，看着你慢慢咽气，你的一切成功都将是我的囊中之物！”"
    },
    {
      "Key": "060a5275-1e0e-41aa-9352-df79ae91b09a",
      "Value": "“精神可嘉！说实话，我会想念你的，真的。等我任命新的指挥官时，我希望可以找到像你一样的人来继任，像你一样勇敢，也像你一样容易利用！”"
    },
    {
      "Key": "b176d039-0f3f-418c-83e7-0015e409d79f",
      "Value": "{n}兰德尔对你露出了悲伤的笑容。{/n}“我们本来真的是朋友的。但是，你也明白，在权力面前，友谊的小船说翻就翻。我很欣赏你，我真的欣赏你。但是你如此热衷于冒险，你在这宝座上也坐不了太久！所以只要我成功了，至少你的领土还可以为{g|House Lebeda}勒贝达家族{/g}所用……相信我，我会衷心地缅怀你的。”"
    },
    {
      "Key": "0cdf4892-0947-46bc-b3f6-47991b20d5f2",
      "Value": "“你认为琳翠是不是应该在她的书中写一章《白痴和把他们变成死掉的白痴的过程》？我的意思是，看看她手上搜集的所有材料！”"
    },
    {
      "Key": "72e38025-3024-4fde-89c5-525af7e261c3",
      "Value": "“那么问题来了！哪个名字听起来更好——‘愚蠢的风袋’，还是‘自命不凡的白痴’？”"
    },
    {
      "Key": "691597e5-c057-4afc-b683-6be12fbc4d49",
      "Value": "“小兰德尔，要是你知道，当你因为这个愚蠢的恶作剧而丧命的时候我有多想你，那该多好。在整个男爵领，你是唯一一个比我更容易恼怒的人！”"
    },
    {
      "Key": "54cbfbb7-4458-45ec-9b1c-e54326e2838c",
      "Value": "“呵，我喜欢你，小伙子……杀了你，我非常抱歉，但是我必须这样做。”"
    },
    {
      "Key": "765af15b-8f1d-4444-8488-f7846ef88dc5",
      "Value": "“如此悲伤、迷途深陷的贵族。兰德尔，你本应该用你的行为来寻求光荣和荣誉——而不是炫耀你的上古血统，玷污了它的名声。"
    },
    {
      "Key": "290a8848-ffef-43cc-98db-72452029df0a",
      "Value": "“什么？”{n}诺克诺克转过头盯着你，完全不知所措。{/n}“你竟然还活着！可是他说你……”{n}地精陷入了沉默，迟来的顿悟表现在了他的脸上。{/n}“噢……”"
    }
  ]
}