{
  "$id": "1",
  "strings": [
    {
      "Key": "ea855d36-c513-4579-9619-4ce5d8b2e11e",
      "Value": "“德雷勒夫男爵？没想到会在这里见到你！”"
    },
    {
      "Key": "d6e1c515-8669-4a21-949e-eb6e7d0d8e5a",
      "Value": "[离开]"
    },
    {
      "Key": "359ca72d-83a8-4521-8293-f62ee1b8b46a",
      "Value": "[杀死男爵]“我会结束你的痛苦。”"
    },
    {
      "Key": "23a4d0b6-9fda-4fb9-a9d3-bcaf61d6a280",
      "Value": "“你死了？”"
    },
    {
      "Key": "a51de47b-e9ee-430f-acff-dc12991ab57f",
      "Value": "“如果你已经死了，那你现在怎么能和我交谈？”"
    },
    {
      "Key": "87dce911-0341-4958-9659-2e39eca3058d",
      "Value": "“你是怎么死的？”"
    },
    {
      "Key": "f34cf8e6-4202-4053-b62b-649565ca164a",
      "Value": "“你在伊洛维提的牢房里干什么？”"
    },
    {
      "Key": "7e3889c2-51c7-4baa-afc3-2852a8de2757",
      "Value": "“你是疯了吗？我觉得你看起来还活得好好的。”"
    },
    {
      "Key": "186efb25-b05a-4a88-af17-789ffb67534b",
      "Value": "[打开牢笼]“不管你是死是活，都没有理由留在这个牢笼里。顺便一提，如果你想起死回生，就到外面去找一个叫德雷·雅恩斯的牧师。告诉他是{Name}让你去找他的，你需要帮助。”"
    },
    {
      "Key": "4f6efd92-86df-4e69-ad5e-fccee37a46e4",
      "Value": "“如果你已经死了，也就是说祭司可以复生你？”"
    },
    {
      "Key": "f2c3dbd0-17d6-457e-9971-c9b7662d786e",
      "Value": "“我有几个问题想问你。”"
    },
    {
      "Key": "3b3af216-17f7-47ef-bfc8-0b5a91d52d2c",
      "Value": "“感谢你的回答。”"
    },
    {
      "Key": "e7070b0c-0fd7-460c-a5f4-30d7fe7be3fa",
      "Value": "[施放侦测魔法]“我们看看这里有什么……”"
    },
    {
      "Key": "04bd83dc-e3b0-434c-9a4c-9b8fd4c414c8",
      "Value": "{n}你差点没有认出这个坐在牢房里的人。与你上次在雷斯托夫的正式场合见到的{d|Drelev}汉尼斯・德雷勒夫{/d}男爵相比，他变得太厉害了。曾经粗壮的胳膊现在似乎一折就断，他皮肤苍白，眼窝凹陷。他坐在地面上，凝视着自己的双手。{/n}"
    },
    {
      "Key": "8815c5f8-3c73-43bc-9a27-a9123cd198c6",
      "Value": "{n}男爵完全没有注意到你的存在。他只是坐着，低头看着地面。{/n}"
    },
    {
      "Key": "8b07f645-26e7-4224-96c8-27e2ed3f295a",
      "Value": "{n}德雷勒夫男爵温顺地接受了死亡。他甚至没有抬起头来。{/n}"
    },
    {
      "Key": "394af933-4978-45b8-8bfa-7395b958513c",
      "Value": "{n}男爵的嘴唇开始颤抖，但是他的目光没有离开自己的双手。就在你开始觉得可能无法从他那里得到回答的时候，他轻声开口了，{/n}“你来得太晚了。汉尼斯･德雷勒夫男爵已经死了。在这里的只是具尸体。”"
    },
    {
      "Key": "a85e870f-42ee-4cf8-8ba1-c62b3f965fd6",
      "Value": "{n}男爵非常轻微地耸了耸肩。{/n}“我不知道。”"
    },
    {
      "Key": "2de3431c-ac7a-49d3-a718-6c086cc8417a",
      "Value": "{n}在一段长时间的沉默之后，汉尼斯简短地回答了你的问题。{/n}“是的。”"
    },
    {
      "Key": "4ff0a2bf-7006-4386-990b-4edc4520a3eb",
      "Value": "“伊洛维提有一个怪物仆从。一条宠物娜迦。它会为他变成不同的形态……但那并不重要。他给了她一把武器。一把木头的剑。大概有魔法。他告诉她用这把剑刺穿德雷勒夫。于是她照做了。然后德雷勒夫死了。”"
    },
    {
      "Key": "313c2d8f-8909-43e6-90d7-6e8c27ad1361",
      "Value": "{n}德雷勒夫十指交叉。{/n}“男爵离开{g|Restov}雷斯托夫{/g}回{g|Glenebon}格伦邦{/g}去的时候。却遇上了一场突袭。伊洛维提屠杀了他的人民，将他活捉。没人支付汉尼斯･德雷勒夫男爵的赎金。于是伊洛维提杀了他。”"
    },
    {
      "Key": "9e8c6c5f-c605-484b-acd0-c2b6abaa9215",
      "Value": "“看仔细些。”{n}德雷勒夫抬起自己的手，用颤抖的手指摸了摸脸颊——他的皮肤惨白，但却算是很健康。{/n}“你瞧？皮肤正在剥落，手指，腐烂到了骨头里，这具尸体没有眼睛，没有心脏，没有肠胃……一个也没有。你闻闻。死肉的臭味。”"
    },
    {
      "Key": "2179feab-89b5-4c32-bc48-887ac64ec8ce",
      "Value": "{n}德雷勒夫没有对你的话作出反应，只是一直低头看着自己的手。{/n}"
    },
    {
      "Key": "11626fb3-1775-4bb7-ab9f-73492ff7458d",
      "Value": "“德雷·雅恩斯，祭司。祭司……可以复生德雷勒夫？”{n}汉尼斯费力地站了起来，离开了牢房，脚步跌跌撞撞。{/n}"
    },
    {
      "Key": "7a53ffc0-d4fa-41da-8593-3c2c74e2a873",
      "Value": "“这……这些问题没有意义。”"
    },
    {
      "Key": "e082c266-f6ef-4cbb-b89e-dbf03d518f39",
      "Value": "“祭司？”{n}汉尼斯无声地动着嘴唇。{/n}“是的，祭司……祭司能够复生死者？是的……也许祭司可以帮上忙。”"
    },
    {
      "Key": "e0f197dc-e5b9-45a8-bfb5-6dbac28454d4",
      "Value": "{n}德雷勒夫男爵没有注意到你。{/n}"
    },
    {
      "Key": "009dab8b-2fdb-4c0c-bf1a-3c3c70c92bd0",
      "Value": "“这个德雷勒夫真是个混账。换作是他肯定不会饶了你的——但你还是救了他。我希望他不要糟蹋了这个重新开始的机会！”"
    },
    {
      "Key": "94971a27-2f26-4025-a7a2-345b7ca1b63a",
      "Value": "“他算是死了一次了——托你的福，他还能死而复生。你给了他第二次机会，就像你曾经对我做的那样。”"
    },
    {
      "Key": "5d20baed-398c-4692-bbfe-1a81080f0c4e",
      "Value": "{n}汉尼斯非常艰难地抬起头看着你。{/n}“谢谢你，{Name}。也许德雷勒夫男爵可以再活一次。”"
    },
    {
      "Key": "d00bfbb1-3969-45ac-93db-6e0cfe76fdce",
      "Value": "{n}似乎德雷勒夫身上并没有正在生效的法术。但是，你注意了到奇怪的魔法灵光的痕迹。你想起来，这和充满老法桐下那个房间的光十分相似，就在那里，你与塔尔图齐奥交手过。这使人猜想，这些痕迹也许是某种强大的神器留下的，但并没有确凿的证据。{/n}"
    }
  ]
}