{
  "$id": "1",
  "strings": [
    {
      "Key": "d3c744ea-c282-4e17-8c84-d5ad8a6e9c62",
      "Value": "[尝试辨析浅浮雕上画的是谁]"
    },
    {
      "Key": "18422696-02b1-4301-ae20-e6eae7ab6bbb",
      "Value": "[走开]"
    },
    {
      "Key": "16d58fd9-7f6f-49e8-a504-9269475fd695",
      "Value": "{n}这幅浅浮雕上画着一个巨型的独眼巨人骨骸。无数个体型较小的独眼巨人攀上他白骨嶙峋的手臂，爬进他那空洞的眼窝，消失在里面。{/n}"
    },
    {
      "Key": "49ae821a-efa3-4c7d-99ce-c680ca16b92b",
      "Value": "{n}这幅浅浮雕描绘的是修建了这座古墓的邪恶神灵之一， {g|Charon}卡戎{/g}，一只以巨大骷髅形象出现的死神的大恶魔。无数个体型较小的独眼巨人攀上他白骨嶙峋的手臂，爬进他那空洞的眼窝，消失在里面。{/n}"
    },
    {
      "Key": "737b62c9-93b7-4379-b0b6-c43a8d70ff67",
      "Value": "{n}耶萨尔抚摸着这块古老的巨石。{/n}“我认得这幅图画。这是{g|Charon}卡戎{/g}，死神的大恶魔，天启四骑士之一。他和指引死者灵魂的{g|Pharasma}法拉丝玛{/g}可不一样。他能够随心所欲地夺走生命，丝毫没有怜悯之心。”"
    },
    {
      "Key": "aac56e7e-3cd1-45e5-bb5f-701e571a9ac9",
      "Value": "“据我所知，至今还有许多崇拜{g|Charon}卡戎{/g}的邪教徒。但我没想到就连独眼巨人也信奉他。”"
    },
    {
      "Key": "8dc97935-b9c9-4a89-b165-e70068527734",
      "Value": "“一面刻着大邪魔的墙！噫，真恶心。我想提议我们毁掉这个地方，然后把一切都一把火烧光。但是不好说……也许这些石头里还有什么危险的保护性法术呢……”"
    },
    {
      "Key": "fb344715-f2e0-4aaa-9f8f-dca434d50b1d",
      "Value": "{n}凯莉柯变得忧心忡忡：{/n}“邪魔的邪恶程度更甚于魔鬼。倘若瓦恩领的消失与这些遗迹有某种关联，那么……那些人太可怜了！”"
    }
  ]
}