{
  "$id": "1",
  "strings": [
    {
      "Key": "daacedca-3645-4a9b-8a13-6f99df7b5de7",
      "Value": "“我完全不明白，究竟是什么驱使着傻瓜们去收集古代的小玩意儿，比如那些独眼巨人或者其他种族的遗物。那些把这作为娱乐方式的人，心脏里涌流的怕不是血液，而是甜牛奶吧。”"
    },
    {
      "Key": "4f68cb9c-4c7f-43e5-bf1c-0696d2da0b50",
      "Value": "“我觉得挺激动人心的——那些数千年前在同一片土地上、同一片天空下自由漫步的生物的踪迹！他们是怎么生活的？他们后来怎么样了？他们的城市如何陷落、如何衰亡？”"
    },
    {
      "Key": "cc1c1a5b-9e5d-454d-8d44-2a4b3cdf2071",
      "Value": "“我已经破解了你那魔法力量的秘密！你脑子里有两块石头一直不停地撞来撞去，想撞出一点思想的火花。但思想的火花没撞出来，倒是撞出来你指尖的火花。”"
    },
    {
      "Key": "4aeb645e-498d-4d34-9b81-23d49749acd9",
      "Value": "“古时的遗迹真是养眼，瑞贡尕，因为它们让我们想到了生命的脆弱。离开这些遗迹的人已经消失了。而现在，我们正追随着他们的步伐。听听那弥留的寂静吧——难道它不能让你心灵平静吗？”"
    }
  ]
}