{
  "$id": "1",
  "strings": [
    {
      "Key": "dccb0b0d-2bae-41e6-b511-7e0fac7787ad",
      "Value": "“如此可悲的荒原。缺少法纪总会导致荒凉和空虚。”"
    },
    {
      "Key": "3ff3050f-de0a-48f1-9de7-ce1dbd4f1ed5",
      "Value": "“我不知道，高特已经不再那样井井有序了——不过也远没到荒凉的地步。”"
    },
    {
      "Key": "7bd9ec2e-7ac2-4889-b082-5d23d59e0b24",
      "Value": "“相信我，法律和秩序可以被人为扭曲，用来为邪恶服务，带来更多的残酷和痛苦。”"
    },
    {
      "Key": "6258f05a-1f97-423d-bf6e-bb17dbfae4f1",
      "Value": "“法律和自由就像天平的两端一样彼此平衡，两者都可以导致邪恶，只有慈悲才能缓和它们。”"
    }
  ]
}