{
  "$id": "1",
  "strings": [
    {
      "Key": "255ee86f-435d-46f3-aafe-ccda161d25e0",
      "Value": "“我不明白……”"
    },
    {
      "Key": "3f70583a-801d-4cae-b018-388edaa3658a",
      "Value": "“发生了什么事？”"
    },
    {
      "Key": "6f82b460-414a-4358-a9fe-896b0def00da",
      "Value": "“你先提出来真是令人宽慰。事实上，我已经厌倦你了。”"
    },
    {
      "Key": "8b492ab0-8f74-4550-840a-608ded83787e",
      "Value": "“我不在乎。我们在一起可以克服任何危险！”"
    },
    {
      "Key": "516d08dc-4b3a-463e-8c0e-8fd53d132edd",
      "Value": "“好吧，我们就照你说的去做。但要知道，你伤了我的心。”"
    },
    {
      "Key": "631b48be-3ba5-443c-bf6d-c357a38ed010",
      "Value": "“那好吧。事实上，这应该很早就发生了。”"
    },
    {
      "Key": "46deea81-f0a7-44b1-abe7-e5abbe1d7d53",
      "Value": "{n}崔斯提安显得憔悴而苍白。他的眼皮沉下来，嘴角悲伤地皱着。{/n}“{name}，我们需要谈谈。”"
    },
    {
      "Key": "762efe44-b502-423f-8fca-8f924499bde3",
      "Value": "“最近……最近我一直有事没事就打扰你。所有那些问题，谈话......还有其他一切......我知道我让你分心了。我很自私，要求你这么注意我。我保证不会再发生这种事了。”"
    },
    {
      "Key": "eb633a17-6ed7-4c24-83e2-f7dea5cf715b",
      "Value": "{n}崔斯提安闭上眼睛转身离开。{/n}“完美。很高兴我们能彼此理解。”"
    },
    {
      "Key": "86a70ab3-b7ad-4a7b-a2e0-9901599c1cae",
      "Value": "{n}崔斯提安畏缩了一下。{/n}“拜托，{name}，不要这样。你是女爵，{g|Stolen Lands}失窃之地{/g}的统治者，守护着数百人。我不能分散你的注意力，尤其......尤其是邻国的一个男爵在这里失踪的时候！同样的危险可能会笼罩着你！要是......我不能让这种事发生！”"
    },
    {
      "Key": "cacdcefe-4af0-4fe6-affa-35d71da9d379",
      "Value": "{n}年轻人挣脱开来，叠着手祈祷。{/n}“我会为你向{g|Sarenrae}莎恩芮{/g}祈祷。”"
    },
    {
      "Key": "10b62a26-9a39-4256-9ca5-dbb6309c41f8",
      "Value": "“不！请想想你自己，想想那些依赖你的人！许多人的命运悬于一线……”{n}崔斯提安叹了口气，{/n}“够了。已经决定了。”"
    },
    {
      "Key": "5ab5961e-b0c1-4fe3-965c-40904b5ff588",
      "Value": "{n}崔斯提安低下头转身离开。{/n}“只是为了帮助你，{name}，只是为了帮助你。”"
    }
  ]
}